{"id": 3994, "name": "WaifuProtogen", "description": "<p>This model is a merge of Protogen v2.2 and Waifu-v1.3, which retains all the knowledge of Waifu-v1.3 and generates high quality anime images</p><p></p><p>WaifuProtogen Recipe for Checkpoint Merger in Automatic1111 webui</p><p>Model A - Protogen v2.2 ( <a target=\"_blank\" rel=\"ugc\" href=\"https://huggingface.co/darkstorm2150/Protogen_v2.2_Official_Release\">https://huggingface.co/darkstorm2150/Protogen_v2.2_Official_Release</a> )</p><p>Model B - Waifu-v1.3 ( <a target=\"_blank\" rel=\"ugc\" href=\"https://huggingface.co/hakurei/waifu-diffusion-v1-3\">https://huggingface.co/hakurei/waifu-diffusion-v1-3</a> )</p><p>Model B - SD-v1.4 ( <a target=\"_blank\" rel=\"ugc\" href=\"https://huggingface.co/CompVis/stable-diffusion-v-1-4-original\">https://huggingface.co/CompVis/stable-diffusion-v-1-4-original</a> )</p><p>Multiplier = 1</p><p>Interpolation Method: \"Add difference\"</p>", "type": "Checkpoint", "poi": false, "nsfw": false, "allowNoCredit": true, "allowCommercialUse": "Sell", "allowDerivatives": true, "allowDifferentLicense": true, "stats": {"downloadCount": 173, "favoriteCount": 18, "commentCount": 0, "ratingCount": 0, "rating": 0}, "creator": {"username": "MindInTheDigits", "image": "https://image.civitai.com/xG1nkqKTMzGDvpLrqFT7WA/3e321523-b741-4c2d-bf5a-1d62fdc70600/width=96/MindInTheDigits.jpeg"}, "tags": ["anime", "base model"], "modelVersions": [{"id": 4443, "modelId": 3994, "name": "1", "createdAt": "2023-01-06T22:19:05.808Z", "updatedAt": "2023-01-06T22:40:50.781Z", "trainedWords": [], "baseModel": "SD 1.5", "earlyAccessTimeFrame": 0, "description": "<p></p>", "stats": {"downloadCount": 137, "ratingCount": 0, "rating": 0}, "files": [{"name": "waifuprotogen_1.safetensors", "id": 4351, "sizeKB": 4165133.693359375, "type": "Model", "metadata": {"fp": "fp16", "size": "full", "format": "SafeTensor"}, "pickleScanResult": "Success", "pickleScanMessage": "No Pickle imports", "virusScanResult": "Success", "scannedAt": "2023-01-06T22:28:48.935Z", "hashes": {"AutoV1": "16E33692", "AutoV2": "65F6C95FC5", "SHA256": "65F6C95FC51F7889C79DFE08785C3CED2A97BF2B2FF0002FD7ED5271B7E0AADB", "CRC32": "EDC3F009", "BLAKE3": "5161F55CCC263C1534B7FDBEA7076BAC316FB9CDCED24B87CB1547540E3A4579"}, "downloadUrl": "https://civitai.com/api/download/models/4443", "primary": true}], "images": [{"id": 30123, "url": "https://image.civitai.com/xG1nkqKTMzGDvpLrqFT7WA/7bfce62f-3747-4128-2d74-246911f3c700/width=450/30123.jpeg", "nsfw": "None", "width": 512, "height": 640, "hash": "UPKBmSID]_g$~N-iItv|=;I[rv-PnhA0n,Nx", "meta": null}, {"id": 30128, "url": "https://image.civitai.com/xG1nkqKTMzGDvpLrqFT7WA/f85d0d41-2b98-4b66-4f8b-feedfcb13b00/width=450/30128.jpeg", "nsfw": "None", "width": 512, "height": 640, "hash": "UuI}FJayt7t6~oayxtbHt8WVoza#ogf6WXj[", "meta": null}, {"id": 30127, "url": "https://image.civitai.com/xG1nkqKTMzGDvpLrqFT7WA/bc8309cd-5eff-42cf-6dbc-b21715b88900/width=450/30127.jpeg", "nsfw": "None", "width": 512, "height": 640, "hash": "UUJ[CpoL_3%M~qf6xut7t7xu%Mof-;M{RjWB", "meta": null}, {"id": 30126, "url": "https://image.civitai.com/xG1nkqKTMzGDvpLrqFT7WA/8ec58e1a-fe01-4d81-b6ed-e8e8957e3c00/width=450/30126.jpeg", "nsfw": "None", "width": 512, "height": 640, "hash": "UlMGF?jZ?^xa%MkCS#ayv~j[R*aetlj[t7of", "meta": null}, {"id": 30125, "url": "https://image.civitai.com/xG1nkqKTMzGDvpLrqFT7WA/339462d8-360c-4a10-c4f0-053487ddae00/width=450/30125.jpeg", "nsfw": "None", "width": 512, "height": 640, "hash": "UiOMQy9Z~q=|-os.R,f8RiV@kCj]sokCt7xa", "meta": null}, {"id": 30131, "url": "https://image.civitai.com/xG1nkqKTMzGDvpLrqFT7WA/a189c7ac-a429-42f7-cbb9-d60525ebe500/width=450/30131.jpeg", "nsfw": "None", "width": 3624, "height": 1868, "hash": "UTPP_t%g~X_2%Ms:kBo2_4aeM{Rj%LfjahWB", "meta": null}], "downloadUrl": "https://civitai.com/api/download/models/4443"}, {"id": 4444, "modelId": 3994, "name": "WaifuProtogen-inpainting", "createdAt": "2023-01-06T22:19:05.808Z", "updatedAt": "2023-01-06T22:40:50.781Z", "trainedWords": [], "baseModel": "SD 1.5", "earlyAccessTimeFrame": 0, "description": "<p>Inpainting version of this model created with this method <a target=\"_blank\" rel=\"ugc\" href=\"https://www.reddit.com/r/StableDiffusion/comments/zyi24j/how_to_turn_any_model_into_an_inpainting_model/\">https://www.reddit.com/r/StableDiffusion/comments/zyi24j/how_to_turn_any_model_into_an_inpainting_model/</a></p>", "stats": {"downloadCount": 36, "ratingCount": 0, "rating": 0}, "files": [{"name": "waifuprotogen_-inpainting.safetensors", "id": 4352, "sizeKB": 4165237.88671875, "type": "Model", "metadata": {"fp": "fp16", "size": "full", "format": "SafeTensor"}, "pickleScanResult": "Success", "pickleScanMessage": "No Pickle imports", "virusScanResult": "Success", "scannedAt": "2023-01-06T22:37:01.277Z", "hashes": {"AutoV1": "27F4A777", "AutoV2": "E4CB833034", "SHA256": "E4CB8330342FDF1FEA82E262AFAB09688E7E67DB664AD67051C941DE2C0702F3", "CRC32": "478E821E", "BLAKE3": "CD2679D34E8CF2295420A2E731B0D6E6EF16155035B63B97B676D0047608B94C"}, "downloadUrl": "https://civitai.com/api/download/models/4444", "primary": true}], "images": [{"id": 30132, "url": "https://image.civitai.com/xG1nkqKTMzGDvpLrqFT7WA/baf9ac39-7c80-4a1e-4c85-634e03a14b00/width=450/30132.jpeg", "nsfw": "None", "width": 1768, "height": 1780, "hash": "UeOp#;oz^+xu~qo0.8a}D%j[t7jsRPWCRia}", "meta": null}], "downloadUrl": "https://civitai.com/api/download/models/4444"}]}