{"id": 4, "name": "Vi from Arcane", "description": "<p>Created by jinofcoolnes and originally uploaded to HuggingFace</p><p><br /></p><p>Check out my patreon for the latest models.</p><p>https://www.patreon.com/Rahmel</p><p><br /></p>", "type": "Checkpoint", "poi": false, "nsfw": false, "allowNoCredit": true, "allowCommercialUse": "Sell", "allowDerivatives": true, "allowDifferentLicense": true, "stats": {"downloadCount": 142, "favoriteCount": 20, "commentCount": 0, "ratingCount": 0, "rating": 0}, "creator": {"username": "jinofcoolnes", "image": "https://image.civitai.com/xG1nkqKTMzGDvpLrqFT7WA/3f49505c-55fe-4031-656f-f4f28fca7300/width=96/jinofcoolnes.jpeg"}, "tags": ["anime", "arcane", "league of legends"], "modelVersions": [{"id": 4, "modelId": 4, "name": "V1", "createdAt": "2022-11-04T17:32:55.939Z", "updatedAt": "2022-11-24T21:17:56.829Z", "trainedWords": ["sks vi", "vi"], "baseModel": "SD 1.5", "earlyAccessTimeFrame": 0, "description": null, "stats": {"downloadCount": 142, "ratingCount": 0, "rating": 0}, "files": [{"name": "viFromArcane_v1.ckpt", "id": 479, "sizeKB": 4165359, "type": "Model", "metadata": {"fp": "fp16", "size": "full", "format": "PickleTensor"}, "pickleScanResult": "Success", "pickleScanMessage": "**Detected Pickle imports (4)**\n```\ntorch.LongStorage\ntorch.FloatStorage\ncollections.OrderedDict\ntorch._utils._rebuild_tensor_v2\n```", "virusScanResult": "Success", "scannedAt": "2022-11-12T09:23:32.851Z", "hashes": {"AutoV1": "E02601F3", "AutoV2": "2DB4E932C1", "SHA256": "2DB4E932C1D7E3AC4B8C9D94D9B9C98487941F3B6C5617973351F898374D7AAE", "CRC32": "D517B99A", "BLAKE3": "706E1292474DEA25A7A7A37EBD73A5F61AA5DCD67BF93434FEE51E8150B7221D"}, "downloadUrl": "https://civitai.com/api/download/models/4", "primary": true}], "images": [{"id": 195, "url": "https://image.civitai.com/xG1nkqKTMzGDvpLrqFT7WA/1be77efb-efad-4618-5b39-2e1dca032300/width=450/195.jpeg", "nsfw": "None", "width": 360, "height": 360, "hash": "UFB.}-~UOqWqD*D+EfW.X8xtxYbHM|jbofNG", "meta": null}, {"id": 194, "url": "https://image.civitai.com/xG1nkqKTMzGDvpLrqFT7WA/bdca3453-e1d2-4ffa-6617-0e526de0b200/width=450/194.jpeg", "nsfw": "None", "width": 360, "height": 360, "hash": "UQH]^9~B~W%L-V5Qb^NaX9xGxGNaof$*t7bu", "meta": null}, {"id": 193, "url": "https://image.civitai.com/xG1nkqKTMzGDvpLrqFT7WA/def88f3f-5a99-43fa-0df6-f49497266900/width=450/193.jpeg", "nsfw": "Soft", "width": 360, "height": 360, "hash": "UDEw%q00}]sS+IXmI.ozbHRPkpRQRQxuIoxu", "meta": null}, {"id": 192, "url": "https://image.civitai.com/xG1nkqKTMzGDvpLrqFT7WA/fbe8666d-2405-4c9d-9a13-957e1b7d5600/width=450/192.jpeg", "nsfw": "None", "width": 453, "height": 680, "hash": "URD*-0~A%ext$jxGxZt6IpS2a|WV%1xZbbI;", "meta": null}], "downloadUrl": "https://civitai.com/api/download/models/4"}]}