{"id": 156, "name": "DnDAi-Flesh_Golem", "description": "<p>Twitter: <a href=\"https://twitter.com/VTTRPGResources\" rel=\"ugc\" target=\"_blank\">https://twitter.com/VTTRPGResources</a></p><p>Checkpoints: <a href=\"https://huggingface.co/VTTRPGResources\" rel=\"ugc\" target=\"_blank\">https://huggingface.co/VTTRPGResources</a></p><p>Discord Server: <a href=\"https://discord.gg/RTzFFx6FfS\" rel=\"ugc\" target=\"_blank\">https://discord.gg/RTzFFx6FfS</a></p><p>Endless Characters: <a href=\"https://www.endlesscharacters.com/index.php?/category/9\" rel=\"ugc\" target=\"_blank\">https://www.endlesscharacters.com/index.php?/category/9</a></p>", "type": "Checkpoint", "poi": false, "nsfw": false, "allowNoCredit": true, "allowCommercialUse": "Sell", "allowDerivatives": true, "allowDifferentLicense": true, "stats": {"downloadCount": 141, "favoriteCount": 44, "commentCount": 1, "ratingCount": 0, "rating": 0}, "creator": {"username": "vttrpgresources", "image": "https://image.civitai.com/xG1nkqKTMzGDvpLrqFT7WA/edaa660c-78f3-4dc9-6ab0-718274b71000/width=96/vttrpgresources.jpeg"}, "tags": [], "modelVersions": [{"id": 172, "modelId": 156, "name": "DnDAi VTTRPGResources Flesh Golem", "createdAt": "2022-11-16T23:31:22.252Z", "updatedAt": "2022-11-18T17:48:47.405Z", "trainedWords": [], "baseModel": "SD 1.5", "earlyAccessTimeFrame": 0, "description": null, "stats": {"downloadCount": 141, "ratingCount": 0, "rating": 0}, "files": [{"name": "dndaiFleshGolem_dndaiVttrpgresources.ckpt", "id": 442, "sizeKB": 2082867.794921875, "type": "Model", "metadata": {"fp": "fp16", "size": "full", "format": "PickleTensor"}, "pickleScanResult": "Success", "pickleScanMessage": "**Detected Pickle imports (3)**\n```\ntorch.HalfStorage\ntorch._utils._rebuild_tensor_v2\ncollections.OrderedDict\n```", "virusScanResult": "Success", "scannedAt": "2022-11-17T23:43:56.136Z", "hashes": {"AutoV1": "25DB7ACB", "AutoV2": "3ECB296988", "SHA256": "3ECB29698876ACE28DC02A865C7825ECC04A5B0FBD629010C221CE7C43FA11A8", "CRC32": "80D6D570", "BLAKE3": "08EFB261BC3B3241298C31CF5FF5538B4A8B7E86C062B92F299E7539C747C5D2"}, "downloadUrl": "https://civitai.com/api/download/models/172", "primary": true}], "images": [{"id": 8230, "url": "https://image.civitai.com/xG1nkqKTMzGDvpLrqFT7WA/f0f7f1fc-a995-4269-1c33-3da2cbd45b00/width=450/8230.jpeg", "nsfw": "None", "width": 512, "height": 512, "hash": "UHC6V[%2yCoy~Vxakqof-;ofS2ba%MofofWV", "meta": null}, {"id": 8228, "url": "https://image.civitai.com/xG1nkqKTMzGDvpLrqFT7WA/7cf7d6ad-8448-47e6-ea29-c6dc8cc38800/width=450/8228.jpeg", "nsfw": "None", "width": 512, "height": 512, "hash": "USECqB_2?uIV~px[x[M{%Mj[a|RjxuayRQRj", "meta": null}], "downloadUrl": "https://civitai.com/api/download/models/172"}]}