{"id": 64663, "name": "\u6c64\u9762\u6862\u5b50", "description": "<p>\u6743\u91cd0.7-0.9\u51fa\u56fe</p><p>\u8d1f\u9762\u8bcd\u7528\u4e86EasyNegative</p><p>\u8bf7\u52ff\u7528\u4e8e\u4efb\u4f55\u5546\u4e1a\u7528\u9014\u548c\u5176\u4ed6\u975e\u6cd5\u7528\u9014\uff0c\u4e25\u683c\u9075\u5b88\u5404\u56fd\u6cd5\u5f8b\u3002<br />\u4e0b\u8f7d\u5373\u8868\u793a\u60a8\u540c\u610f\u4e0a\u8ff0\u534f\u8bae\u3002</p><p>\u70b9\u83dc\u7fa4\uff1a<a target=\"_blank\" rel=\"ugc\" href=\"https://t.me/+0TaXk67vTZ9jNDZl\">https://t.me/+0TaXk67vTZ9jNDZl</a></p>", "type": "LORA", "poi": false, "nsfw": false, "allowNoCredit": true, "allowCommercialUse": "Sell", "allowDerivatives": true, "allowDifferentLicense": true, "stats": {"downloadCount": 967, "favoriteCount": 231, "commentCount": 2, "ratingCount": 1, "rating": 3}, "creator": {"username": "EVERDREAM", "image": "https://image.civitai.com/xG1nkqKTMzGDvpLrqFT7WA/c45037ea-339e-4ebe-9c85-e36fd8006f3e/width=96/EVERDREAM.jpeg"}, "tags": ["photorealistic", "woman", "celebrity", "girls"], "modelVersions": [{"id": 69294, "modelId": 64663, "name": "v1.0", "createdAt": "2023-05-13T03:47:49.241Z", "updatedAt": "2023-05-13T03:49:19.503Z", "trainedWords": [], "baseModel": "SD 1.5", "earlyAccessTimeFrame": 0, "description": null, "stats": {"downloadCount": 967, "ratingCount": 1, "rating": 3}, "files": [{"name": "\u6c64\u9762V3.safetensors", "id": 48429, "sizeKB": 36978.6708984375, "type": "Model", "metadata": {"fp": null, "size": null, "format": "SafeTensor"}, "pickleScanResult": "Success", "pickleScanMessage": "No Pickle imports", "virusScanResult": "Success", "scannedAt": "2023-05-13T03:51:20.795Z", "hashes": {"AutoV1": "9E6F2CD8", "AutoV2": "9E96339547", "SHA256": "9E96339547A7E24460309BCD4568C97B6307EB36A705818D422D66B77D004CAB", "CRC32": "60BF4C51", "BLAKE3": "C79C1F04D73C9B94DE9579D77288116849D1AE1398A58135310F49DB6952E2B8"}, "downloadUrl": "https://civitai.com/api/download/models/69294", "primary": true}], "images": [{"id": 773068, "url": "https://image.civitai.com/xG1nkqKTMzGDvpLrqFT7WA/1fad5fc8-71e4-4e01-8543-2484cf2ac6fc/width=450/773068.jpeg", "nsfw": "Soft", "width": 512, "height": 768, "hash": "UEIE2_4T024n~V9GOZMy0KXA$$kWIo%2Vss,", "meta": null}, {"id": 773069, "url": "https://image.civitai.com/xG1nkqKTMzGDvpLrqFT7WA/c556f1e4-e30c-4c9d-8d73-1636f319d544/width=450/773069.jpeg", "nsfw": "None", "width": 512, "height": 768, "hash": "UFFhx4^ix?^*00~p-o-:%LMx-:9Z9akBnOt8", "meta": null}], "downloadUrl": "https://civitai.com/api/download/models/69294"}]}