{"id": 40341, "name": "Tsubaki Miyajima \u5bae\u5cf6\u693f | Saimin Seishidou \u50ac\u7720\u6027\u6307\u5c0e", "description": "<p>Tsubaki Miyajima \u5bae\u5cf6\u693f | Saimin Seishidou \u50ac\u7720\u6027\u6307\u5c0e</p><p><a target=\"_blank\" rel=\"ugc\" href=\"https://www.pixiv.net/users/86166786\">https://www.pixiv.net/users/86166786</a></p><p></p><p>Discord: Picture Share (Uncensorship) <a target=\"_blank\" rel=\"ugc\" href=\"https://discord.gg/YkqSnaXqEQ\">https://discord.gg/YkqSnaXqEQ</a></p><p><a target=\"_blank\" rel=\"ugc\" href=\"https://discord.com/channels/1105857326503690320/1120292266272096277/1121329673893314670\">https://discord.com/channels/1105857326503690320/1120292266272096277/1121329673893314670</a></p><p></p><p>Training Images : 113</p><p><br />Version 1 : Bigger File , include CG / Manga</p><p>Version 2 : Smaller File , Only Capture From Anime</p><p></p><p>prompt:</p><p>(Night:1.7), Japan, Tokyo, CityView, Before Window,<br /><br />Standing at attention,<br /><br />(White_kimono:1.3),cleavage,<br /><br />&lt;lora:Tsubaki_Miyajima_Saimin_Seishidou-KK77-V2:0.7&gt;,<br /><br />black_hair, long_hair, hair_pulled_back,parted_lips,purple_eyes, braid,<br /><br />1 girl, 24yo,mature female,Beautiful Finger,Beautiful long legs,Beautiful body,Beautiful Nose,Beautiful character design, perfect eyes, perfect face,<br /><br />looking at viewer, in the center of the image,<br /><br />NSFW,official art,extremely detailed CG unity 8k wallpaper, perfect lighting,Colorful, Bright_Front_face_Lighting,<br />(masterpiece:1.0),(best_quality:1.0), ultra high res,4K,ultra-detailed,<br />photography, 8K, HDR, highres, absurdres:1.2, Kodak portra 400, film grain, blurry background, bokeh:1.2, lens flare, (vibrant_color:1.2)<br /><br />(Beautiful,large_Breasts:1.4), (beautiful_face:1.5),(narrow_waist),</p><p><br />Negative prompt:</p><p>EasyNegative, FastNegativeV2, bad-artist-anime, bad-hands-5, lowres, bad anatomy, bad hands, text, error, missing fingers, extra digit, fewer digits, cropped, jpeg artifacts, signature, watermark, username, blurry, out of focus, censorship, Missing vagina, Blurry faces, Blank faces, bad face, Ugly, extra ear, amputee, missing hands, missing arms, missing legs, Extra fingers, 6 fingers, Extra feet, Missing nipples, ghost, futanari, Extra legs, Extra hands, panties,pants, (painting by bad-artist-anime:0.9), (painting by bad-artist:0.9), text, error, blurry, jpeg artifacts, cropped, normal quality, artist name, (worst quality, low quality:1.4),twisted_hands,fused_fingers,<br /><br />Steps: 48, Sampler: Euler a, CFG scale: 7, Seed: , Size: 512x768,</p><p>Model hash: 3e9211917c, Model: yesmix_v16Original,</p><p>Denoising strength: 0.5, Hires upscale: 2, Hires steps: 20,</p><p>Hires upscaler: R-ESRGAN 4x+ Anime6B,</p><p>Lora hashes: \"Tsubaki_Miyajima_Saimin_Seishidou-KK77-V2: e645b8e5a3ad\", Version: v1.3.1</p><p></p><p></p><p>Another Negative prompt: For Real human</p><p>EasyNegative, paintings, sketches, (worst quality:2), (low quality:2), (normal quality:2), lowres, normal quality, ((monochrome)), ((grayscale)), skin spots, acnes, skin blemishes, age spot, (outdoor:1.6), manboobs, backlight,(ugly:1.331), (duplicate:1.331), (morbid:1.21), (mutilated:1.21), (tranny:1.331), mutated hands, (poorly drawn hands:1.331), blurry, (bad anatomy:1.21), (bad proportions:1.331), extra limbs, (disfigured:1.331), (more than 2 nipples:1.331), (missing arms:1.331), (extra legs:1.331), (fused fingers:1.61051), (too many fingers:1.61051), (unclear eyes:1.331), bad hands, missing fingers, extra digit, (futa:1.1), bad body, NG_DeepNegative_V1_75T,pubic hair, glans</p><p></p><p>Steps: 64, Sampler: DPM++ SDE Karras, CFG scale: 7,</p><p>Seed: , Size: 512x768, Model hash: fc2511737a,</p><p>Model: chilloutmix_NiPrunedFp32Fix,</p><p>Lora hashes:</p><p>\"Tsubaki_Miyajima_Saimin_Seishidou-KK77-V2: e645b8e5a3ad,</p><p>Yuuko_Kiryuu_RapeLay-V1: 3e5876dda6c7\", Version: v1.3.1</p>", "type": "LORA", "poi": false, "nsfw": false, "allowNoCredit": true, "allowCommercialUse": "Sell", "allowDerivatives": true, "allowDifferentLicense": true, "stats": {"downloadCount": 2663, "favoriteCount": 584, "commentCount": 2, "ratingCount": 4, "rating": 4.75}, "creator": {"username": "Kisaku_KK77", "image": "https://image.civitai.com/xG1nkqKTMzGDvpLrqFT7WA/ba5d788b-ceed-4037-b030-2236ee7d9332/width=96/Kisaku_KK77.jpeg"}, "tags": ["anime", "character", "sexy", "female", "woman"], "modelVersions": [{"id": 101393, "modelId": 40341, "name": "v2.0 Only Anime", "createdAt": "2023-06-22T06:02:39.915Z", "updatedAt": "2023-06-22T06:03:17.918Z", "trainedWords": [], "baseModel": "SD 1.5", "earlyAccessTimeFrame": 0, "description": null, "stats": {"downloadCount": 851, "ratingCount": 0, "rating": 0}, "files": [{"name": "Tsubaki_Miyajima_Saimin_Seishidou-KK77-V2.safetensors", "id": 70904, "sizeKB": 22244.716796875, "type": "Model", "metadata": {"fp": null, "size": null, "format": "SafeTensor"}, "pickleScanResult": "Success", "pickleScanMessage": "No Pickle imports", "virusScanResult": "Success", "scannedAt": "2023-06-22T06:05:34.083Z", "hashes": {"AutoV1": "440C0FFC", "AutoV2": "2E9C9942E2", "SHA256": "2E9C9942E2124C42202C8C052F086C01DCE2602FCB5921FAF8CF72D9ECF07E1D", "CRC32": "4D39D81A", "BLAKE3": "B712DDF93862A5296F3E32F510A24582A6974A9C47B92B98090EDD29AD86599D"}, "downloadUrl": "https://civitai.com/api/download/models/101393", "primary": true}, {"name": "Tsubaki_Miyajima_Saimin_Seishidou.zip", "id": 70905, "sizeKB": 20475.1279296875, "type": "Training Data", "metadata": {"fp": null, "size": null, "format": "Other"}, "pickleScanResult": "Success", "pickleScanMessage": "No Pickle imports", "virusScanResult": "Success", "scannedAt": "2023-06-22T06:05:35.223Z", "hashes": {"AutoV1": "0A4F31B9", "AutoV2": "C31FD266CA", "SHA256": "C31FD266CA5D437E2F6D94069785C368BE7F7DC7E769D43E6075F98608699E1D", "CRC32": "1D60C435", "BLAKE3": "ED53D54E0DCC78366ED8DCE1475016F246CC3B3EF78474AF419B1C793C15D642"}, "downloadUrl": "https://civitai.com/api/download/models/101393?type=Training%20Data"}], "images": [{"id": 1240699, "url": "https://image.civitai.com/xG1nkqKTMzGDvpLrqFT7WA/22b20569-74af-4101-9e2a-8114b549fff3/width=450/1240699.jpeg", "nsfw": "Soft", "width": 1024, "height": 1536, "hash": "UWKAW-~WVW#*00IUNLa#56W;o#R.RjWAxttR", "meta": {"Size": "512x768", "seed": 2168604075, "Model": "yesmix_v16Original", "steps": 48, "hashes": {"model": "3e9211917c", "embed:bad-hands-5": "aa7651be15", "embed:easynegative": "c74b4e810b", "embed:FastNegativeV2": "a7465e7cc2", "embed:bad-artist-anime": "5f7bea8875", "lora:Tsubaki_Miyajima_Saimin_Seishidou-KK77-V2": "2e9c9942e2"}, "prompt": "(Night:1.7), Japan, Tokyo, CityView, Before Window,\nStanding at attention,\n(White_kimono:1.3),cleavage,\n<lora:Tsubaki_Miyajima_Saimin_Seishidou-KK77-V2:0.7>,\nblack_hair, long_hair, hair_pulled_back,parted_lips,purple_eyes, braid,\n1 girl, 24yo,mature female,Beautiful Finger,Beautiful long legs,Beautiful body,Beautiful Nose,Beautiful character design, perfect eyes, perfect face,\nlooking at viewer, in the center of the image,\nNSFW,official art,extremely detailed CG unity 8k wallpaper, perfect lighting,Colorful, Bright_Front_face_Lighting,\n(masterpiece:1.0),(best_quality:1.0), ultra high res,4K,ultra-detailed,\nphotography, 8K, HDR, highres, absurdres:1.2, Kodak portra 400, film grain, blurry background, bokeh:1.2, lens flare, (vibrant_color:1.2)\n(Beautiful,large_Breasts:1.4), (beautiful_face:1.5),(narrow_waist),", "Version": "v1.3.1", "sampler": "Euler a", "cfgScale": 7, "resources": [{"hash": "3e9211917c", "name": "yesmix_v16Original", "type": "model"}], "Model hash": "3e9211917c", "Hires steps": "20", "Hires upscale": "2", "Hires upscaler": "R-ESRGAN 4x+ Anime6B", "negativePrompt": "EasyNegative, FastNegativeV2, bad-artist-anime, bad-hands-5, lowres, bad anatomy, bad hands, text, error, missing fingers, extra digit, fewer digits, cropped, jpeg artifacts, signature, watermark, username, blurry, out of focus, censorship, Missing vagina, Blurry faces, Blank faces, bad face, Ugly, extra ear, amputee, missing hands, missing arms, missing legs, Extra fingers, 6 fingers, Extra feet, Missing nipples, ghost, futanari, Extra legs, Extra hands, panties,pants, (painting by bad-artist-anime:0.9), (painting by bad-artist:0.9), text, error, blurry, jpeg artifacts, cropped, normal quality, artist name, (worst quality, low quality:1.4),twisted_hands,fused_fingers,", "Denoising strength": "0.5", "\"Tsubaki_Miyajima_Saimin_Seishidou-KK77-V2": "e645b8e5a3ad\""}}, {"id": 1240743, "url": "https://image.civitai.com/xG1nkqKTMzGDvpLrqFT7WA/d201f2ff-d0bb-44b2-955f-98c12754e81a/width=450/1240743.jpeg", "nsfw": "Soft", "width": 1024, "height": 1536, "hash": "UKJai;nh00?vrU^,%Moyt3S5-o^*~qIo%1V?", "meta": {"Size": "512x768", "seed": 1990721578, "Model": "yesmix_v16Original", "steps": 64, "hashes": {"model": "3e9211917c", "embed:bad-hands-5": "aa7651be15", "embed:easynegative": "c74b4e810b", "embed:FastNegativeV2": "a7465e7cc2", "embed:bad-artist-anime": "5f7bea8875", "lora:Tsubaki_Miyajima_Saimin_Seishidou-KK77-V2": "2e9c9942e2"}, "prompt": "(Night:1.7), Japan, Tokyo, CityView, Before Window,\nStanding at attention,\n(White_kimono:1.3),cleavage,\n<lora:Tsubaki_Miyajima_Saimin_Seishidou-KK77-V2:0.7>,\nblack_hair, long_hair, hair_pulled_back,parted_lips,purple_eyes, braid,\n1 girl, 24yo,mature female,Beautiful Finger,Beautiful long legs,Beautiful body,Beautiful Nose,Beautiful character design, perfect eyes, perfect face,\nlooking at viewer, in the center of the image,\nNSFW,official art,extremely detailed CG unity 8k wallpaper, perfect lighting,Colorful, Bright_Front_face_Lighting,\n(masterpiece:1.0),(best_quality:1.0), ultra high res,4K,ultra-detailed,\nphotography, 8K, HDR, highres, absurdres:1.2, Kodak portra 400, film grain, blurry background, bokeh:1.2, lens flare, (vibrant_color:1.2)\n(Beautiful,large_Breasts:1.4), (beautiful_face:1.5),(narrow_waist),", "Version": "v1.3.1", "sampler": "Euler a", "cfgScale": 7, "resources": [{"hash": "3e9211917c", "name": "yesmix_v16Original", "type": "model"}], "Model hash": "3e9211917c", "Hires steps": "20", "Hires upscale": "2", "Hires upscaler": "R-ESRGAN 4x+ Anime6B", "negativePrompt": "EasyNegative, FastNegativeV2, bad-artist-anime, bad-hands-5, lowres, bad anatomy, bad hands, text, error, missing fingers, extra digit, fewer digits, cropped, jpeg artifacts, signature, watermark, username, blurry, out of focus, censorship, Missing vagina, Blurry faces, Blank faces, bad face, Ugly, extra ear, amputee, missing hands, missing arms, missing legs, Extra fingers, 6 fingers, Extra feet, Missing nipples, ghost, futanari, Extra legs, Extra hands, panties,pants, (painting by bad-artist-anime:0.9), (painting by bad-artist:0.9), text, error, blurry, jpeg artifacts, cropped, normal quality, artist name, (worst quality, low quality:1.4),twisted_hands,fused_fingers,", "Denoising strength": "0.5", "\"Tsubaki_Miyajima_Saimin_Seishidou-KK77-V2": "e645b8e5a3ad\""}}, {"id": 1240941, "url": "https://image.civitai.com/xG1nkqKTMzGDvpLrqFT7WA/2b8d4fef-2b86-4656-a3d9-6f3bc3cf4ea5/width=450/1240941.jpeg", "nsfw": "Soft", "width": 512, "height": 768, "hash": "UJJkJ|v#0fvz0J00.TNGD%Io%2RP-;x^vzof", "meta": {"Size": "512x768", "seed": 348043508, "Model": "chilloutmix_NiPrunedFp32Fix", "steps": 64, "hashes": {"model": "fc2511737a", "embed:bad-hands-5": "aa7651be15", "embed:easynegative": "c74b4e810b", "embed:FastNegativeV2": "a7465e7cc2", "embed:bad-artist-anime": "5f7bea8875", "lora:Miyako_DOA5LR-KK77-V1": "e5451ce87b", "lora:Tsubaki_Miyajima_Saimin_Seishidou-KK77-V2": "2e9c9942e2"}, "prompt": "(Night:1.7), Japan, Tokyo, CityView, Before Window,\nStanding at attention,\n(White_kimono:1.3),cleavage,\n<lora:Tsubaki_Miyajima_Saimin_Seishidou-KK77-V2:0.7>,<lora:Miyako_DOA5LR-KK77-V1:0.3>,\nblack_hair, long_hair, hair_pulled_back,parted_lips,purple_eyes, braid,\n1 girl, 24yo,mature female,Beautiful Finger,Beautiful long legs,Beautiful body,Beautiful Nose,Beautiful character design, perfect eyes, perfect face,\nlooking at viewer, in the center of the image,\nNSFW,official art,extremely detailed CG unity 8k wallpaper, perfect lighting,Colorful, Bright_Front_face_Lighting,\n(masterpiece:1.0),(best_quality:1.0), ultra high res,4K,ultra-detailed,\nphotography, 8K, HDR, highres, absurdres:1.2, Kodak portra 400, film grain, blurry background, bokeh:1.2, lens flare, (vibrant_color:1.2)\n(Beautiful,large_Breasts:1.4), (beautiful_face:1.5),(narrow_waist),", "Version": "v1.3.1", "sampler": "DPM++ SDE Karras", "cfgScale": 7, "resources": [{"hash": "fc2511737a", "name": "chilloutmix_NiPrunedFp32Fix", "type": "model"}], "Model hash": "fc2511737a", "negativePrompt": "EasyNegative, FastNegativeV2, bad-artist-anime, bad-hands-5, paintings, sketches, (worst quality:2), (low quality:2), (normal quality:2), lowres, normal quality, ((monochrome)), ((grayscale)), skin spots, acnes, skin blemishes, age spot, (outdoor:1.6), manboobs, backlight,(ugly:1.331), (duplicate:1.331), (morbid:1.21), (mutilated:1.21), (tranny:1.331), mutated hands, (poorly drawn hands:1.331), blurry, (bad anatomy:1.21), (bad proportions:1.331), extra limbs, (disfigured:1.331), (more than 2 nipples:1.331), (missing arms:1.331), (extra legs:1.331), (fused fingers:1.61051), (too many fingers:1.61051), (unclear eyes:1.331), bad hands, missing fingers, extra digit, (futa:1.1), bad body, NG_DeepNegative_V1_75T,pubic hair, glans", "Miyako_DOA5LR-KK77-V1": "f4cd8f7c3032\"", "\"Tsubaki_Miyajima_Saimin_Seishidou-KK77-V2": "e645b8e5a3ad"}}, {"id": 1240942, "url": "https://image.civitai.com/xG1nkqKTMzGDvpLrqFT7WA/c4a93885-2e08-47c9-aef9-c18aa21e919d/width=450/1240942.jpeg", "nsfw": "Soft", "width": 512, "height": 768, "hash": "UJKmqh+s03R%0h-5_4IU1PD%?Gbb^*%Mnini", "meta": {"Size": "512x768", "seed": 3445798644, "Model": "chilloutmix_NiPrunedFp32Fix", "steps": 64, "hashes": {"model": "fc2511737a", "embed:bad-hands-5": "aa7651be15", "embed:easynegative": "c74b4e810b", "embed:FastNegativeV2": "a7465e7cc2", "embed:bad-artist-anime": "5f7bea8875", "lora:Yuuko_Kiryuu_RapeLay-V1": "bb51d7fee1", "lora:Tsubaki_Miyajima_Saimin_Seishidou-KK77-V2": "2e9c9942e2"}, "prompt": "(Night:1.7), Japan, Tokyo, CityView, Before Window,\nStanding at attention,\n(White_kimono:1.3),cleavage,\n<lora:Tsubaki_Miyajima_Saimin_Seishidou-KK77-V2:0.7>,<lora:Yuuko_Kiryuu_RapeLay-V1:0.3>,\nblack_hair, long_hair, hair_pulled_back,parted_lips,purple_eyes, braid,\n1 girl, 24yo,mature female,Beautiful Finger,Beautiful long legs,Beautiful body,Beautiful Nose,Beautiful character design, perfect eyes, perfect face,\nlooking at viewer, in the center of the image,\nNSFW,official art,extremely detailed CG unity 8k wallpaper, perfect lighting,Colorful, Bright_Front_face_Lighting,\n(masterpiece:1.0),(best_quality:1.0), ultra high res,4K,ultra-detailed,\nphotography, 8K, HDR, highres, absurdres:1.2, Kodak portra 400, film grain, blurry background, bokeh:1.2, lens flare, (vibrant_color:1.2)\n(Beautiful,large_Breasts:1.4), (beautiful_face:1.5),(narrow_waist),", "Version": "v1.3.1", "sampler": "DPM++ SDE Karras", "cfgScale": 7, "resources": [{"hash": "fc2511737a", "name": "chilloutmix_NiPrunedFp32Fix", "type": "model"}], "Model hash": "fc2511737a", "negativePrompt": "EasyNegative, FastNegativeV2, bad-artist-anime, bad-hands-5, paintings, sketches, (worst quality:2), (low quality:2), (normal quality:2), lowres, normal quality, ((monochrome)), ((grayscale)), skin spots, acnes, skin blemishes, age spot, (outdoor:1.6), manboobs, backlight,(ugly:1.331), (duplicate:1.331), (morbid:1.21), (mutilated:1.21), (tranny:1.331), mutated hands, (poorly drawn hands:1.331), blurry, (bad anatomy:1.21), (bad proportions:1.331), extra limbs, (disfigured:1.331), (more than 2 nipples:1.331), (missing arms:1.331), (extra legs:1.331), (fused fingers:1.61051), (too many fingers:1.61051), (unclear eyes:1.331), bad hands, missing fingers, extra digit, (futa:1.1), bad body, NG_DeepNegative_V1_75T,pubic hair, glans", "Yuuko_Kiryuu_RapeLay-V1": "3e5876dda6c7\"", "\"Tsubaki_Miyajima_Saimin_Seishidou-KK77-V2": "e645b8e5a3ad"}}], "downloadUrl": "https://civitai.com/api/download/models/101393"}, {"id": 45654, "modelId": 40341, "name": "v1.0 Anime+CG", "createdAt": "2023-04-14T17:18:45.914Z", "updatedAt": "2023-06-22T06:03:39.354Z", "trainedWords": [], "baseModel": "SD 1.5", "earlyAccessTimeFrame": 0, "description": null, "stats": {"downloadCount": 1812, "ratingCount": 4, "rating": 4.75}, "files": [{"name": "TsubakiMiyajimaV1.safetensors", "id": 34118, "sizeKB": 169385.7470703125, "type": "Model", "metadata": {"fp": null, "size": null, "format": "SafeTensor"}, "pickleScanResult": "Success", "pickleScanMessage": "No Pickle imports", "virusScanResult": "Success", "scannedAt": "2023-04-14T17:25:50.612Z", "hashes": {"AutoV1": "AFA5F6C6", "AutoV2": "C918694291", "SHA256": "C918694291EECD664ED925301C1D44EBFF498472A6700F7941069A38BAB2DEA1", "CRC32": "296BB5DA", "BLAKE3": "3A9FD9DA926995DAFC4B66B8D6911B734D7D7CE3F6B68ECFD4A19E08DD48DB4F"}, "downloadUrl": "https://civitai.com/api/download/models/45654", "primary": true}], "images": [{"id": 797230, "url": "https://image.civitai.com/xG1nkqKTMzGDvpLrqFT7WA/f274d52b-e737-44d1-ac1f-3e850f42bd9a/width=450/797230.jpeg", "nsfw": "X", "width": 608, "height": 920, "hash": "UKLWn%000JIWM@E3tS-oMdM~.8Ri_MDjococ", "meta": {"Size": "512x768", "seed": 192532016, "Model": "yesmix_v16Original", "steps": 60, "hashes": {"vae": "f921fb3f29", "model": "3e9211917c", "embed:bad-hands-5": "aa7651be15", "lora:saiminSeishidou": "9cf4897d86", "lora:aiueOkaStyle_v10": "db050d7a02", "embed:bad-artist-anime": "5f7bea8875"}, "prompt": "(Night:1.7), east asian architecture, \nsitting at attention,sitting on Tatami,\nWhite_kimono,\n<lora:TsubakiMiyajimaV1:0.85>,<lora:aiueOkaStyle_v10:0.1>, <lora:saiminSeishidou:0.1>,\nblack_hair, long_hair, hair_pulled_back,parted_lips,purple_eyes, braid,\n1 girl, Manga,20yo,mature female,Beautiful Finger,Beautiful long legs,Beautiful body,Beautiful Nose,Beautiful character design, perfect eyes, perfect face,\nlooking at viewer,(innocent_big_eyes:1.0),(Light_smile:1.0),\nofficial art,extremely detailed CG unity 8k wallpaper, perfect lighting,Colorful, Bright_Front_face_Lighting,\n(masterpiece:1.0),(best_quality:1.0), ultra high res,4K,ultra-detailed,\nphotography, 8K, HDR, highres, absurdres:1.2, Kodak portra 400, film grain, blurry background, bokeh:1.2, lens flare, (vibrant_color:1.2)\n(Beautiful,large_Breasts:1.4), (beautiful_face:1.5),(narrow_waist),", "Version": "v1.2.1", "sampler": "Euler a", "cfgScale": 7, "resources": [{"name": "TsubakiMiyajimaV1", "type": "lora", "weight": 0.85}, {"name": "aiueOkaStyle_v10", "type": "lora", "weight": 0.1}, {"name": "saiminSeishidou", "type": "lora", "weight": 0.1}, {"hash": "3e9211917c", "name": "yesmix_v16Original", "type": "model"}], "Model hash": "3e9211917c", "Hires steps": "18", "Hires upscale": "1.2", "Hires upscaler": "Latent", "negativePrompt": "EasyNegative, bad-artist-anime, bad-hands-5, lowres, bad anatomy, bad hands, text, error, missing fingers, extra digit, fewer digits, cropped, jpeg artifacts, signature, (watermark:1.6), username, blurry, out of focus, censorship, Missing vagina, Blurry faces, Blank faces, bad face, Ugly, extra ear, amputee, missing hands, missing arms, missing legs, Extra fingers, 6 fingers, Extra feet, Missing nipples, ghost, futanari, Extra legs, Extra hands, panties,pants, (painting by bad-artist-anime:0.9), (painting by bad-artist:0.9), text, error, blurry, jpeg artifacts, cropped, normal quality, artist name, (worst quality, low quality:1.4),twisted_hands,fused_fingers,", "Denoising strength": "0.5"}}, {"id": 797189, "url": "https://image.civitai.com/xG1nkqKTMzGDvpLrqFT7WA/001e269f-4a35-4442-bb61-fbb459a28238/width=450/797189.jpeg", "nsfw": "None", "width": 608, "height": 920, "hash": "ULLzXJ0i4TIt00E1R+xtM|IU_3RO_4IV%1M|", "meta": {"Size": "512x768", "seed": 3320837292, "Model": "yesmix_v16Original", "steps": 60, "hashes": {"vae": "f921fb3f29", "model": "3e9211917c", "embed:bad-hands-5": "aa7651be15", "lora:saiminSeishidou": "9cf4897d86", "lora:aiueOkaStyle_v10": "db050d7a02", "embed:bad-artist-anime": "5f7bea8875"}, "prompt": "(Night:1.7), east asian architecture, \nsitting at attention,sitting on Tatami,\nWhite_kimono,\n<lora:TsubakiMiyajimaV1:0.85>,<lora:aiueOkaStyle_v10:0.1>, <lora:saiminSeishidou:0.1>,\nblack_hair, long_hair, hair_pulled_back,parted_lips,purple_eyes, braid,\n1 girl, Manga,20yo,mature female,Beautiful Finger,Beautiful long legs,Beautiful body,Beautiful Nose,Beautiful character design, perfect eyes, perfect face,\nlooking at viewer,(innocent_big_eyes:1.0),(expressionless:1.3),\nofficial art,extremely detailed CG unity 8k wallpaper, perfect lighting,Colorful, Bright_Front_face_Lighting,\n(masterpiece:1.0),(best_quality:1.0), ultra high res,4K,ultra-detailed,\nphotography, 8K, HDR, highres, absurdres:1.2, Kodak portra 400, film grain, blurry background, bokeh:1.2, lens flare, (vibrant_color:1.2)\n(Beautiful,large_Breasts:1.4), (beautiful_face:1.5),(narrow_waist),", "Version": "v1.2.1", "sampler": "Euler a", "cfgScale": 7, "resources": [{"name": "TsubakiMiyajimaV1", "type": "lora", "weight": 0.85}, {"name": "aiueOkaStyle_v10", "type": "lora", "weight": 0.1}, {"name": "saiminSeishidou", "type": "lora", "weight": 0.1}, {"hash": "3e9211917c", "name": "yesmix_v16Original", "type": "model"}], "Model hash": "3e9211917c", "Hires steps": "18", "Hires upscale": "1.2", "Hires upscaler": "Latent", "negativePrompt": "EasyNegative, bad-artist-anime, bad-hands-5, lowres, bad anatomy, bad hands, text, error, missing fingers, extra digit, fewer digits, cropped, jpeg artifacts, signature, (watermark:1.6), username, blurry, out of focus, censorship, Missing vagina, Blurry faces, Blank faces, bad face, Ugly, extra ear, amputee, missing hands, missing arms, missing legs, Extra fingers, 6 fingers, Extra feet, Missing nipples, ghost, futanari, Extra legs, Extra hands, panties,pants, (painting by bad-artist-anime:0.9), (painting by bad-artist:0.9), text, error, blurry, jpeg artifacts, cropped, normal quality, artist name, (worst quality, low quality:1.4),twisted_hands,fused_fingers,", "Denoising strength": "0.5"}}, {"id": 797217, "url": "https://image.civitai.com/xG1nkqKTMzGDvpLrqFT7WA/ae046958-c0de-4461-9b96-d90f2de9a0d9/width=450/797217.jpeg", "nsfw": "None", "width": 608, "height": 920, "hash": "UIM?_HtBIoRQ0001oh9GD*4;_NNaTN-=RQ%M", "meta": {"Size": "512x768", "seed": 918304654, "Model": "yesmix_v16Original", "steps": 60, "hashes": {"vae": "f921fb3f29", "model": "3e9211917c", "embed:bad-hands-5": "aa7651be15", "lora:saiminSeishidou": "9cf4897d86", "lora:aiueOkaStyle_v10": "db050d7a02", "embed:bad-artist-anime": "5f7bea8875"}, "prompt": "(Night:1.7), east asian architecture, \nsitting at attention,sitting on Tatami,\nWhite_kimono,\n<lora:TsubakiMiyajimaV1:0.85>,<lora:aiueOkaStyle_v10:0.1>, <lora:saiminSeishidou:0.1>,\nblack_hair, long_hair, hair_pulled_back,parted_lips,purple_eyes, braid,\n1 girl, Manga,20yo,mature female,Beautiful Finger,Beautiful long legs,Beautiful body,Beautiful Nose,Beautiful character design, perfect eyes, perfect face,\nlooking at viewer,(innocent_big_eyes:1.0),(Light_smile:0.3),\nofficial art,extremely detailed CG unity 8k wallpaper, perfect lighting,Colorful, Bright_Front_face_Lighting,\n(masterpiece:1.0),(best_quality:1.0), ultra high res,4K,ultra-detailed,\nphotography, 8K, HDR, highres, absurdres:1.2, Kodak portra 400, film grain, blurry background, bokeh:1.2, lens flare, (vibrant_color:1.2)\n(Beautiful,large_Breasts:1.4), (beautiful_face:1.5),(narrow_waist),", "Version": "v1.2.1", "sampler": "Euler a", "cfgScale": 7, "resources": [{"name": "TsubakiMiyajimaV1", "type": "lora", "weight": 0.85}, {"name": "aiueOkaStyle_v10", "type": "lora", "weight": 0.1}, {"name": "saiminSeishidou", "type": "lora", "weight": 0.1}, {"hash": "3e9211917c", "name": "yesmix_v16Original", "type": "model"}], "Model hash": "3e9211917c", "Hires steps": "18", "Hires upscale": "1.2", "Hires upscaler": "Latent", "negativePrompt": "EasyNegative, bad-artist-anime, bad-hands-5, lowres, bad anatomy, bad hands, text, error, missing fingers, extra digit, fewer digits, cropped, jpeg artifacts, signature, (watermark:1.6), username, blurry, out of focus, censorship, Missing vagina, Blurry faces, Blank faces, bad face, Ugly, extra ear, amputee, missing hands, missing arms, missing legs, Extra fingers, 6 fingers, Extra feet, Missing nipples, ghost, futanari, Extra legs, Extra hands, panties,pants, (painting by bad-artist-anime:0.9), (painting by bad-artist:0.9), text, error, blurry, jpeg artifacts, cropped, normal quality, artist name, (worst quality, low quality:1.4),twisted_hands,fused_fingers,", "Denoising strength": "0.5"}}, {"id": 494154, "url": "https://image.civitai.com/xG1nkqKTMzGDvpLrqFT7WA/9a82741d-9dab-4f49-a13f-cc0dff345300/width=450/494154.jpeg", "nsfw": "X", "width": 512, "height": 768, "hash": "UGLDr*D48^#jth-4~qt3E057_LS~?a?aV?xu", "meta": {"steps": 27, "prompt": "\u5730\u70b9\uff1a(Night:1.7), Hong Kong View, High-rise_hotel,in a room with a window behind her and a curtain behind her,\n\u52a8\u4f5c\uff1asitting on couch\n\u670d\u9970\uff1aWhite_kimono,cleavage,\n\u89d2\u8272\uff1a <lora:saiminSeishidou:0.1>,<lora:TsubakiMiyajimaV1:0.7>,Tsubaki Miyajima,\n\u5934\u53d1\uff1ablack_hair, long_hair, hair_pulled_back,parted_lips,purple_eyes, braid,\n\u89d2\u8272\u9396\u5b9a\uff1a\n1 girl,Solo, Manga,20yo,mature female,Beautiful Finger,Beautiful long legs,Beautiful body,Beautiful Nose,Beautiful character design, perfect eyes, perfect face,\n\u773c\u795e\u8868\u60c5\uff1a\nlooking at viewer, (innocent_big_eyes:1.0),alluring,seductive smile,embarrassed, shy,\n\u756b\u8cea:\nofficial art,extremely detailed CG unity 8k wallpaper, perfect lighting,Colorful, Bright_Front_face_Lighting,\n(masterpiece:1.0),(best_quality:1.0), ultra high res,4K,ultra-detailed,\nphotography, 8K, HDR, highres, absurdres:1.2, Kodak portra 400, film grain, blurry background, bokeh:1.2, lens flare, (vibrant_color:1.2)\n\u8eab\u6750:\n(Beautiful,large_Breasts:1.4), (beautiful_face:1.5),(narrow_waist),", "sampler": "DPM++ 2M", "cfgScale": 7, "negativePrompt": "EasyNegative, lowres, bad anatomy, bad hands, text, error, missing fingers, extra digit, fewer digits, cropped, jpeg artifacts, signature, watermark, username, blurry, out of focus, censorship, Missing vagina, Blurry faces, Blank faces, bad face, Ugly, extra ear, amputee, missing hands, missing arms, missing legs, Extra fingers, 6 fingers, Extra feet, Missing nipples, ghost, futanari, Extra legs, Extra hands, panties,pants, (painting by bad-artist-anime:0.9), (painting by bad-artist:0.9), text, error, blurry, jpeg artifacts, cropped, normal quality, artist name, (worst quality, low quality:1.4),"}}, {"id": 494127, "url": "https://image.civitai.com/xG1nkqKTMzGDvpLrqFT7WA/ac8d4e7a-2dcc-4048-e31c-23bd2cfcdc00/width=450/494127.jpeg", "nsfw": "Soft", "width": 512, "height": 768, "hash": "UGKdGPMf0}n,GH^j%Oxb}[xt^+MzDi-oivRj", "meta": {"steps": 27, "prompt": "\u5730\u70b9\uff1a(Night:1.7), Hong Kong View, High-rise_hotel,in a room with a window behind her and a curtain behind her,\n\u52a8\u4f5c\uff1asitting on couch\n\u670d\u9970\uff1aWhite_kimono,cleavage,\n\u89d2\u8272\uff1a <lora:saiminSeishidou:0.1>,<lora:TsubakiMiyajimaV1:0.7>,Tsubaki Miyajima,\n\u5934\u53d1\uff1ablack_hair, long_hair, hair_pulled_back,parted_lips,purple_eyes, braid,\n\u89d2\u8272\u9396\u5b9a\uff1a\n1 girl,Solo, Manga,20yo,mature female,Beautiful Finger,Beautiful long legs,Beautiful body,Beautiful Nose,Beautiful character design, perfect eyes, perfect face,\n\u773c\u795e\u8868\u60c5\uff1a\nlooking at viewer, (innocent_big_eyes:1.0),alluring,seductive smile,embarrassed, shy,\n\u756b\u8cea:\nofficial art,extremely detailed CG unity 8k wallpaper, perfect lighting,Colorful, Bright_Front_face_Lighting,\n(masterpiece:1.0),(best_quality:1.0), ultra high res,4K,ultra-detailed,\nphotography, 8K, HDR, highres, absurdres:1.2, Kodak portra 400, film grain, blurry background, bokeh:1.2, lens flare, (vibrant_color:1.2)\n\u8eab\u6750:\n(Beautiful,large_Breasts:1.4), (beautiful_face:1.5),(narrow_waist),", "sampler": "DPM++ 2M Karras", "cfgScale": 7, "negativePrompt": "EasyNegative, lowres, bad anatomy, bad hands, text, error, missing fingers, extra digit, fewer digits, cropped, jpeg artifacts, signature, watermark, username, blurry, out of focus, censorship, Missing vagina, Blurry faces, Blank faces, bad face, Ugly, extra ear, amputee, missing hands, missing arms, missing legs, Extra fingers, 6 fingers, Extra feet, Missing nipples, ghost, futanari, Extra legs, Extra hands, panties,pants, (painting by bad-artist-anime:0.9), (painting by bad-artist:0.9), text, error, blurry, jpeg artifacts, cropped, normal quality, artist name, (worst quality, low quality:1.4),"}}, {"id": 797226, "url": "https://image.civitai.com/xG1nkqKTMzGDvpLrqFT7WA/0d054105-6e27-42bf-a76c-2157d0346c23/width=450/797226.jpeg", "nsfw": "None", "width": 608, "height": 920, "hash": "UFKT}g5[0000005B-=tj03_4%h^*E.s;E0x[", "meta": {"Size": "512x768", "seed": 1087450718, "Model": "yesmix_v16Original", "steps": 60, "hashes": {"vae": "f921fb3f29", "model": "3e9211917c", "embed:bad-hands-5": "aa7651be15", "lora:saiminSeishidou": "9cf4897d86", "lora:aiueOkaStyle_v10": "db050d7a02", "embed:bad-artist-anime": "5f7bea8875"}, "prompt": "(Night:1.7), east asian architecture, \nsitting at attention,sitting on Tatami,\nWhite_kimono,\n<lora:TsubakiMiyajimaV1:0.85>,<lora:aiueOkaStyle_v10:0.1>, <lora:saiminSeishidou:0.1>,\nblack_hair, long_hair, hair_pulled_back,parted_lips,purple_eyes, braid,\n1 girl, Manga,20yo,mature female,Beautiful Finger,Beautiful long legs,Beautiful body,Beautiful Nose,Beautiful character design, perfect eyes, perfect face,\nlooking at viewer,(innocent_big_eyes:1.0),(Light_smile:0.7),\nofficial art,extremely detailed CG unity 8k wallpaper, perfect lighting,Colorful, Bright_Front_face_Lighting,\n(masterpiece:1.0),(best_quality:1.0), ultra high res,4K,ultra-detailed,\nphotography, 8K, HDR, highres, absurdres:1.2, Kodak portra 400, film grain, blurry background, bokeh:1.2, lens flare, (vibrant_color:1.2)\n(Beautiful,large_Breasts:1.4), (beautiful_face:1.5),(narrow_waist),", "Version": "v1.2.1", "sampler": "Euler a", "cfgScale": 7, "resources": [{"name": "TsubakiMiyajimaV1", "type": "lora", "weight": 0.85}, {"name": "aiueOkaStyle_v10", "type": "lora", "weight": 0.1}, {"name": "saiminSeishidou", "type": "lora", "weight": 0.1}, {"hash": "3e9211917c", "name": "yesmix_v16Original", "type": "model"}], "Model hash": "3e9211917c", "Hires steps": "18", "Hires upscale": "1.2", "Hires upscaler": "Latent", "negativePrompt": "EasyNegative, bad-artist-anime, bad-hands-5, lowres, bad anatomy, bad hands, text, error, missing fingers, extra digit, fewer digits, cropped, jpeg artifacts, signature, (watermark:1.6), username, blurry, out of focus, censorship, Missing vagina, Blurry faces, Blank faces, bad face, Ugly, extra ear, amputee, missing hands, missing arms, missing legs, Extra fingers, 6 fingers, Extra feet, Missing nipples, ghost, futanari, Extra legs, Extra hands, panties,pants, (painting by bad-artist-anime:0.9), (painting by bad-artist:0.9), text, error, blurry, jpeg artifacts, cropped, normal quality, artist name, (worst quality, low quality:1.4),twisted_hands,fused_fingers,", "Denoising strength": "0.5"}}], "downloadUrl": "https://civitai.com/api/download/models/45654"}]}